genie_flow_invoker/invoker/weaviate/__init__.py
genie_flow_invoker/invoker/weaviate/base.py
genie_flow_invoker/invoker/weaviate/client.py
genie_flow_invoker/invoker/weaviate/delete.py
genie_flow_invoker/invoker/weaviate/exceptions.py
genie_flow_invoker/invoker/weaviate/model.py
genie_flow_invoker/invoker/weaviate/persist.py
genie_flow_invoker/invoker/weaviate/properties.py
genie_flow_invoker/invoker/weaviate/search.py
genie_flow_invoker/invoker/weaviate/utils.py
genie_flow_invoker_weaviate-0.9.1.dist-info/licenses/NOTICES
genie_flow_invoker_weaviate-0.9.1.dist-info/METADATA
genie_flow_invoker_weaviate-0.9.1.dist-info/WHEEL
genie_flow_invoker_weaviate-0.9.1.dist-info/top_level.txt
genie_flow_invoker_weaviate-0.9.1.dist-info/RECORD
